PySimplePreview/__init__.py
PySimplePreview/__main__.py
PySimplePreview/di.py
PySimplePreview/data/__init__.py
PySimplePreview/data/config_storage.py
PySimplePreview/data/di.py
PySimplePreview/data/previews_storage.py
PySimplePreview/domain/__init__.py
PySimplePreview/domain/di.py
PySimplePreview/domain/interactor/__init__.py
PySimplePreview/domain/interactor/files_observer.py
PySimplePreview/domain/interactor/module_loader.py
PySimplePreview/domain/interactor/previews_manager.py
PySimplePreview/domain/interactor/abc/__init__.py
PySimplePreview/domain/interactor/abc/files_observer.py
PySimplePreview/domain/interactor/abc/module_loader.py
PySimplePreview/domain/model/__init__.py
PySimplePreview/domain/model/config.py
PySimplePreview/domain/model/event.py
PySimplePreview/domain/model/log_config.py
PySimplePreview/domain/model/position.py
PySimplePreview/domain/model/preview.py
PySimplePreview/view/__init__.py
PySimplePreview/view/app.py
PySimplePreview/view/contracts.py
PySimplePreview/view/di.py
PySimplePreview/view/layouts.py
PySimplePreview/view/log.py
PySimplePreview/view/models.py
PySimplePreview/view/api/__init__.py
PySimplePreview/view/api/_types.py
PySimplePreview/view/api/_utils.py
PySimplePreview/view/api/core.py
PySimplePreview/view/controller/__init__.py
PySimplePreview/view/controller/base.py
PySimplePreview/view/controller/external_preview.py
PySimplePreview/view/controller/external_preview_factory.py
PySimplePreview/view/controller/preview_settings.py
PySimplePreview/view/controller/system_args_handler.py
PySimplePreview/view/controller/utils.py
PySimplePreview-0.0.2.dist-info/LICENSE.md
PySimplePreview-0.0.2.dist-info/METADATA
PySimplePreview-0.0.2.dist-info/WHEEL
PySimplePreview-0.0.2.dist-info/entry_points.txt
PySimplePreview-0.0.2.dist-info/top_level.txt
PySimplePreview-0.0.2.dist-info/RECORD
