Metadata-Version: 2.1
Name: PySimplePreview
Version: 0.0.2
Summary: Realtime (live/hot) preview of PySimpleGUI layouts
Author: MaxBQb
License: MIT License
Project-URL: Homepage, https://github.com/MaxBQb/PySimplePreview
Project-URL: Bug Tracker, https://github.com/MaxBQb/PySimplePreview/issues
Keywords: PySimpleGUI,preview,live-preview,realtime-preview,GUI
Classifier: Programming Language :: Python :: 3
Classifier: Intended Audience :: Developers
Classifier: Natural Language :: English
Classifier: Programming Language :: Python :: Implementation :: CPython
Classifier: Topic :: Software Development :: Libraries :: Python Modules
Requires-Python: >=3.11
License-File: LICENSE.md
Requires-Dist: PySimpleGUI (==4.60.5)
Requires-Dist: watchdog (==3.0.0)
Requires-Dist: jsons (==1.6.3)
Requires-Dist: punq (==0.6.2)
